clicksignlib/__init__.py
clicksignlib/adapters/__init__.py
clicksignlib/adapters/aiohttp_adapter.py
clicksignlib/adapters/httpx_adapter.py
clicksignlib/adapters/irequests.py
clicksignlib/click_sign.py
clicksignlib/environments/__init__.py
clicksignlib/environments/environment_abc.py
clicksignlib/environments/prod_env.py
clicksignlib/environments/protocols/__init__.py
clicksignlib/environments/protocols/ienvironment.py
clicksignlib/environments/testing_env.py
clicksignlib/handlers/__init__.py
clicksignlib/handlers/batch_handler/__init__.py
clicksignlib/handlers/batch_handler/batch_handler.py
clicksignlib/handlers/config.py
clicksignlib/handlers/document_handler/__init__.py
clicksignlib/handlers/document_handler/document_handler.py
clicksignlib/handlers/embedded_handler/__init__.py
clicksignlib/handlers/embedded_handler/embedded_handler.py
clicksignlib/handlers/mixins/__init__.py
clicksignlib/handlers/mixins/endpoint_mixin.py
clicksignlib/handlers/notification_handler/__init__.py
clicksignlib/handlers/notification_handler/notification_handler.py
clicksignlib/handlers/signatory_handler/__init__.py
clicksignlib/handlers/signatory_handler/auths_type.py
clicksignlib/handlers/signatory_handler/signatory_handler.py
clicksignlib/handlers/signatory_handler/signer_type.py
clicksignlib/handlers/template_handler/__init__.py
clicksignlib/handlers/template_handler/template_handler.py
clicksignlib/run_in_asyncio.py
clicksignlib/utils/__init__.py
clicksignlib/utils/bytes_to_base64.py
clicksignlib/utils/calc_hmac_sum.py
clicksignlib/utils/errors/__init__.py
clicksignlib/utils/errors/api_error.py
clicksignlib/utils/errors/invalid_key.py
clicksignlib/utils/result.py
clicksignlib/utils/validators/__init__.py
clicksignlib/utils/validators/uuid_validator.py
clicksignlib/utils/validators/validator_abc.py
clicksignlib-1.1.9.dist-info/METADATA
clicksignlib-1.1.9.dist-info/WHEEL
clicksignlib-1.1.9.dist-info/RECORD
